Workbook

Sheet Gastos 1º ano
J2: Disponibilidade de investimento | K2: ='Disponibilidade e 1ºENTRADA'!D14 -> 5600
E3: Despesas únicas | F3: Despesas mensais | G3: Despesas anuais | J3: Projeção de gastos 1ºano | K3: =E4+E5+E6+SUM(F7:F8)*12+G9 -> 5587
A4: Sociedade anonima? | D4: Abrir empresa | E4: =300+75 -> 375 | J4: Margem | K4: =K2-K3 -> 13
A5: Sociedade p quotas | D5: Construção do PA | E5: 5200
D6: Carrinha
D7: Contabilista
D8: Aluguer de um espaço
D9: Domínio de um site? | G9: 12

Sheet Disponibilidade  e 1ºENTRADA
E2: Projeção 1º ano (entrada): | F2: ='Gastos 1º ano'!K3 -> 5587
D4: Disponibilidade de investimento | E4: Percentagem de investimento | F4: Valor da primeira entrada
C5: Mateus Rocchi | E5: =D5/SUM(($D$5:$D$13)) -> 0 | F5: =$F$2*E5 -> 0
C6: Henrique Carneiro | D6: 3900 | E6: =D6/SUM(($D$5:$D$13)) -> 0.69642857 | F6: =$F$2*E6 -> 3890.9464
C7: José Silva | D7: 500 | E7: =D7/SUM(($D$5:$D$13)) -> 0.089285714 | F7: =$F$2*E7 -> 498.83929
C8: Rui Alves | D8: 500 | E8: =D8/SUM(($D$5:$D$13)) -> 0.089285714 | F8: =$F$2*E8 -> 498.83929
C9: Rodrigo Capelas | D9: 300 | E9: =D9/SUM(($D$5:$D$13)) -> 0.053571429 | F9: =$F$2*E9 -> 299.30357
C10: João Castro | D10: 200 | E10: =D10/SUM(($D$5:$D$13)) -> 0.035714286 | F10: =$F$2*E10 -> 199.53571
C11: Nicolau Teixeira | E11: =D11/SUM(($D$5:$D$13)) -> 0 | F11: =$F$2*E11 -> 0
C12: Inês César | D12: 200 | E12: =D12/SUM(($D$5:$D$13)) -> 0.035714286 | F12: =$F$2*E12 -> 199.53571
C13: Catarina | E13: =D13/SUM(($D$5:$D$13)) -> 0 | F13: =$F$2*E13 -> 0
C14: Total: | D14: =SUM(D5:D13) -> 5600 | E14: =SUM(E5:E13) -> 1 | F14: =SUM(F5:F13) -> 5587
D17: Opção FINANCIAMENTO
D18: 6000 | E18: 10000
D19: 7500 | E19: 7500
D20: 500 | E20: 500
D21: 600 | E21: 600
D22: 300 | E22: 300
D23: 300 | E23: 300
D25: 200 | E25: 200
D26: Opção FINANCIAMENTO
D27: 10000
D28: 7500
D29: 500
D30: 600
D31: 300
D32: 300
D34: 200
D35: Opção FINANCIAMENTO
D36: 2000
D37: 7500
D38: 500
D39: 600
D40: 300
D41: 300
D43: 200

Sheet Divisão de Quotas
C2: 1º ENTRADA | D2: Percentagem | E2: Valor de Quota por investimento | F2: Valor de Quota por trabalho | G2: Quota total
B3: Mateus Rocchi | C3: ='Disponibilidade e 1ºENTRADA'!F5 -> 0 | D3: =C3/SUM($C$3:$C$11) -> 0 | E3: =D3*$J$6 -> 0 | F3: 0.06 | G3: =E3+F3 -> 0.06
B4: Henrique Carneiro | C4: ='Disponibilidade e 1ºENTRADA'!F6 -> 3890.9464 | D4: =C4/SUM($C$3:$C$11) -> 0.69642857 | E4: =D4*$J$6 -> 0.20892857 | F4: 0.12 | G4: =E4+F4 -> 0.32892857
B5: José Silva | C5: ='Disponibilidade e 1ºENTRADA'!F7 -> 498.83929 | D5: =C5/SUM($C$3:$C$11) -> 0.089285714 | E5: =D5*$J$6 -> 0.026785714 | F5: 0.12 | G5: =E5+F5 -> 0.14678571 | I5: Quota por trabalho: | J5: 0.7
B6: Rui Alves | C6: ='Disponibilidade e 1ºENTRADA'!F8 -> 498.83929 | D6: =C6/SUM($C$3:$C$11) -> 0.089285714 | E6: =D6*$J$6 -> 0.026785714 | F6: 0.13 | G6: =E6+F6 -> 0.15678571 | I6: Quota por Investimento: | J6: 0.3
B7: Rodrigo Capelas | C7: ='Disponibilidade e 1ºENTRADA'!F9 -> 299.30357 | D7: =C7/SUM($C$3:$C$11) -> 0.053571429 | E7: =D7*$J$6 -> 0.016071429 | F7: 0.13 | G7: =E7+F7 -> 0.14607143
B8: João Castro | C8: ='Disponibilidade e 1ºENTRADA'!F10 -> 199.53571 | D8: =C8/SUM($C$3:$C$11) -> 0.035714286 | E8: =D8*$J$6 -> 0.010714286 | F8: 0.07 | G8: =E8+F8 -> 0.080714286 | I8: Administação | J8: Rui Alves
B9: Nicolau Teixeira | C9: ='Disponibilidade e 1ºENTRADA'!F11 -> 0 | D9: =C9/SUM($C$3:$C$11) -> 0 | E9: =D9*$J$6 -> 0 | G9: =E9+F9 -> 0 | J9: José Silva
B10: Inês César | C10: ='Disponibilidade e 1ºENTRADA'!F12 -> 199.53571 | D10: =C10/SUM($C$3:$C$11) -> 0.035714286 | E10: =D10*$J$6 -> 0.010714286 | F10: 0.07 | G10: =E10+F10 -> 0.080714286
B11: Catarina | C11: ='Disponibilidade e 1ºENTRADA'!F13 -> 0 | D11: =C11/SUM($C$3:$C$11) -> 0 | E11: =D11*$J$6 -> 0 | G11: =E11+F11 -> 0 | I11: Marketing e Comunicação | J11: Henrique Carneiro
B12: Total: | C12: =SUM(C3:C8) -> 5387.4643 | D12: =SUM(D3:D11) -> 1 | E12: =SUM(E3:E11) -> 0.3 | F12: =SUM(F3:F11) -> 0.7 | G12: =SUM(G3:G11) -> 1 | J12: Mateus Rocchi
I14: Operações | J14: Rodrigo Capelas
I16: Staff | J16: Joao Castro
F17: Opção 2 | J17: Inês César
F18: 0.06
F19: 0.12
F20: 0.12
F21: 0.13
F22: 0.13
F23: 0.07
F25: 0.07
F27: Opção 1
F28: 0.05
F29: 0.07
F30: 0.1
F31: 0.11
F32: 0.11
F33: 0.07
F34: 0.07
F35: 0.07
F36: 0.05

Sheet Lucros
B2: TUDO SUJEITO IVA
C4: PA inteiro | D4: 1/2 PA | F4: Valor bruto : | G4: =C5 -> 550 | H4: Percentagens: | J4: Mateus Rocchi | K4: {='Disponibilidade e 1ºENTRADA'!D5:D10} -> 0 | L4: =K4/SUM($K$4:$K$9) -> 0 | M4: =L4*$G$7 -> 0
B5: Aluguer | C5: 550 | D5: 250 | F5: Caixa | G5: =H5*$G$4 -> 302.5 | H5: 0.55 | J5: Henrique Carneiro | K5: 3900 | L5: =K5/SUM($K$4:$K$9) -> 0.72222222 | M5: =L5*$G$7 -> 35.75
F6: Serviço | G6: =H6*$G$4 -> 126.5 | H6: 0.23 | J6: José Silva | K6: 500 | L6: =K6/SUM($K$4:$K$9) -> 0.092592593 | M6: =L6*$G$7 -> 4.5833333
F7: Royalty (Total) | G7: =H7*$G$4 -> 49.5 | H7: 0.09 | J7: Rui Alves | K7: 500 | L7: =K7/SUM($K$4:$K$9) -> 0.092592593 | M7: =L7*$G$7 -> 4.5833333
B8: Venda | F8: Contacto | G8: =H8*$G$4 -> 5.5 | H8: 0.01 | J8: Rodrigo Capelas | K8: 300 | L8: =K8/SUM($K$4:$K$9) -> 0.055555556 | M8: =L8*$G$7 -> 2.75
B9: Preço | F9: IRC | G9: =H9*$G$4 -> 8.25 | H9: 0.015 | J9: João Castro | K9: 200 | L9: =K9/SUM($K$4:$K$9) -> 0.037037037 | M9: =L9*$G$7 -> 1.8333333
B10: Preço (c/IVA) | F10: Transporte | G10: =H10*$G$4 -> 55 | H10: 0.1 | J10: TOTAL: | L10: =SUM(L4:L9) -> 1 | M10: =L10*$G$7 -> 49.5
B11: Custos | F11: Preço total (c/IVA) | G11: =$C$5+$C$5*0.23 -> 676.5 | H11: 0.23
B12: Lucro | F12: Total em % : | H12: =SUM(H5,H6,H7,H8,H9,H10) -> 0.995
