Workbook

Sheet PROJETO DE AUDIO
D2: PROJETO DE AUDIO C/ INSTALAÇÃO E MANUTENÇÃO
B4: PROPOSTA: | C4: 2º | E4: CLIENTE: | F4: AE ISEP
B5: DATA: | C5: 46159 | E5: CONDIÇÕES PAGAMENTO: | F5: Pré-pagamento
B6: VALIDADE: | C6: 30 dias | E6: PORTES DE ENVIO | F6: 10
B7: PRAZO ENTREGA: | C7: 1/2 semanas (desde o dia da aprovação) | E7: PAGINAS | F7: 1 de 1
B10: QUANTIDADE | C10: DESIGNAÇÃO / DESCRIÇÃO | D10: PREÇO/UN (€) | E10: SUB-TOTAL (€) | F10: TOTAL c/IVA (€)
B11: 1
C12: Behringer Xenyx | E12: A encomendar pelo cliente
C13: X1832USB
B14: 2
C15: Audibax Arkansas 8 | D15: =101*1 -> 101 | E15: =D15*B14 -> 202 | F15: =E15*1.23 -> 248.46
C16: Coluna ativa 2 vias 8" c/ Bluetooth, 80W RMS, XLR/RCA/1/8"
B17: 1
C18: Audibax MC XLR 164 30 | D18: =126*1.254 -> 158.004 | E18: =D18*B17 -> 158.004 | F18: =E18*1.23 -> 194.34492
C19: Stage Box 30m — 16 ins / 4 outs
B20: 4
C21: Cabo XLR/XLR 50m | D21: =48.386556*1.291655 -> 62.498737 | E21: 250 | F21: =E21*1.23 -> 307.5
C22: 3-Pin XLR c/ fichas Amphenol
B23: 1
C24: Restauro e Reabilitação de Coluna | D24: 90 | E24: =D24*B23 -> 90 | F24: =E24 -> 90
C25: Parte elétrica e estrutural
B26: 1
C27: Acessórios de montagem | D27: 20 | E27: =D27*B26 -> 20 | F27: =E27 -> 20
C28: Abraçadeiras de aluminio/plástico, Fita Termo Retratil, etc.
D57: TOTAL | F57: =SUM(F15,F18,F21,F6,F24,F27) -> 870.30492
A59: NOTAS: Preços por unidade apresentados não incluem IVA.Orçamento sujeito a revisões.
B61: MINDSET soundsystem | D61: mind7sound@outllook.com

Sheet IVA
B2: DISCRIMINAÇÃO DE IVA
B4: Taxa IVA: | C4: 0.23
B6: QTD | C6: DESIGNAÇÃO | D6: PREÇO/UN S/IVA (€) | E6: SUB-TOTAL S/IVA (€) | F6: IVA (€) | G6: TOTAL C/IVA (€)
B7: ='PROJETO DE AUDIO'!B11 -> 1 | C7: ='PROJETO DE AUDIO'!C12&" "&'PROJETO DE AUDIO'!C13 -> Behringer Xenyx X1832USB | F7: =E7*$C$4 -> 0 | G7: =E7+F7 -> 0
B8: ='PROJETO DE AUDIO'!B14 -> 2 | C8: ='PROJETO DE AUDIO'!C15&" "&'PROJETO DE AUDIO'!C16 -> Audibax Arkansas 8 Coluna ativa 2 vias 8" c/ Bluetooth, 80W RMS, XLR/RCA/1/8" | D8: ='PROJETO DE AUDIO'!D15 -> 101 | E8: ='PROJETO DE AUDIO'!E15 -> 202 | F8: =E8*$C$4 -> 46.46 | G8: =E8+F8 -> 248.46
B9: ='PROJETO DE AUDIO'!B17 -> 1 | C9: ='PROJETO DE AUDIO'!C18&" "&'PROJETO DE AUDIO'!C19 -> Audibax MC XLR 164 30 Stage Box 30m — 16 ins / 4 outs | D9: ='PROJETO DE AUDIO'!D18 -> 158.004 | E9: ='PROJETO DE AUDIO'!E18 -> 158.004 | F9: =E9*$C$4 -> 36.34092 | G9: =E9+F9 -> 194.34492
B10: ='PROJETO DE AUDIO'!B20 -> 4 | C10: ='PROJETO DE AUDIO'!C21&" "&'PROJETO DE AUDIO'!C22 -> Cabo XLR/XLR 50m 3-Pin XLR c/ fichas Amphenol | D10: ='PROJETO DE AUDIO'!D21 -> 62.498737 | E10: ='PROJETO DE AUDIO'!E21 -> 250 | F10: =E10*$C$4 -> 57.5 | G10: =E10+F10 -> 307.5
B11: ='PROJETO DE AUDIO'!B23 -> 1 | C11: ='PROJETO DE AUDIO'!C24&" "&'PROJETO DE AUDIO'!C25 -> Restauro e Reabilitação de Coluna Parte elétrica e estrutural | D11: ='PROJETO DE AUDIO'!D24 -> 90 | E11: ='PROJETO DE AUDIO'!E24 -> 90 | F11: =E11*$C$4 -> 20.7 | G11: =E11+F11 -> 110.7
B12: ='PROJETO DE AUDIO'!B26 -> 1 | C12: ='PROJETO DE AUDIO'!C27&" "&'PROJETO DE AUDIO'!C28 -> Acessórios de montagem Abraçadeiras de aluminio/plástico, Fita Termo Retratil, etc. | D12: ='PROJETO DE AUDIO'!D27 -> 20 | E12: ='PROJETO DE AUDIO'!E27 -> 20 | F12: =E12*$C$4 -> 4.6 | G12: =E12+F12 -> 24.6
C13: Portes de envio | E13: ='PROJETO DE AUDIO'!F6 -> 10 | F13: =E13*$C$4 -> 2.3 | G13: =E13+F13 -> 12.3
C15: TOTAIS | E15: =SUM(E7:E13) -> 730.004 | F15: =SUM(F7:F13) -> 167.90092 | G15: =SUM(G7:G13) -> 897.90492
B17: Total S/IVA: | C17: =E15 -> 730.004
B18: Total IVA: | C18: =F15 -> 167.90092
B19: Total C/IVA: | C19: =G15 -> 897.90492
